calco_prueba/__init__.py
calco_prueba-1.0.5.dist-info/LICENSE
calco_prueba-1.0.5.dist-info/METADATA
calco_prueba-1.0.5.dist-info/WHEEL
calco_prueba-1.0.5.dist-info/top_level.txt
calco_prueba-1.0.5.dist-info/RECORD
