Metadata-Version: 2.1
Name: calco-prueba
Version: 1.0.5
Summary: Calco_prueba
Author: Kirill
Author-email: analyst1@calconut.es
Classifier: Programming Language :: Python :: 3
Classifier: License :: OSI Approved :: MIT License
Classifier: Operating System :: OS Independent
Requires-Python: >=3.8
License-File: LICENSE
